capo/__init__.py
capo/__main__.py
capo/errors.py
capo/functions.py
capo/params.py
capo-0.6.dist-info/licenses/AUTHORS.md
capo-0.6.dist-info/licenses/LICENSE
capo-0.6.dist-info/METADATA
capo-0.6.dist-info/WHEEL
capo-0.6.dist-info/top_level.txt
capo-0.6.dist-info/RECORD
